CHANGES.rst
CONTRIBUTORS.rst
LICENSE.GPL
LICENSE.rst
MANIFEST.in
README.rst
TODO.rst
setup.cfg
setup.py
bobtemplates/__init__.py
bobtemplates.eea.egg-info/PKG-INFO
bobtemplates.eea.egg-info/SOURCES.txt
bobtemplates.eea.egg-info/dependency_links.txt
bobtemplates.eea.egg-info/entry_points.txt
bobtemplates.eea.egg-info/namespace_packages.txt
bobtemplates.eea.egg-info/not-zip-safe
bobtemplates.eea.egg-info/requires.txt
bobtemplates.eea.egg-info/top_level.txt
bobtemplates/eea/__init__.py
bobtemplates/eea/addon.py
bobtemplates/eea/base.py
bobtemplates/eea/behavior.py
bobtemplates/eea/bobregistry.py
bobtemplates/eea/buildout.py
bobtemplates/eea/content_type.py
bobtemplates/eea/portlet.py
bobtemplates/eea/restapi_service.py
bobtemplates/eea/theme.py
bobtemplates/eea/theme_barceloneta.py
bobtemplates/eea/theme_package.py
bobtemplates/eea/utils.py
bobtemplates/eea/view.py
bobtemplates/eea/viewlet.py
bobtemplates/eea/vocabulary.py
bobtemplates/eea/addon/.editorconfig
bobtemplates/eea/addon/.gitattributes
bobtemplates/eea/addon/.gitignore.bob
bobtemplates/eea/addon/.mrbob.ini
bobtemplates/eea/addon/.travis.yml.bob
bobtemplates/eea/addon/CONTRIBUTING.md.bob
bobtemplates/eea/addon/Jenkinsfile.bob
bobtemplates/eea/addon/MANIFEST.in.bob
bobtemplates/eea/addon/README.rst.bob
bobtemplates/eea/addon/setup.py.bob
bobtemplates/eea/addon/tox.ini
bobtemplates/eea/addon/+package.namespace+/__init__.py
bobtemplates/eea/addon/+package.namespace+/+package.namespace2+/__init__.py
bobtemplates/eea/addon/+package.namespace+/+package.namespace2+/+package.name+/README.txt.bob
bobtemplates/eea/addon/+package.namespace+/+package.namespace2+/+package.name+/__init__.py.bob
bobtemplates/eea/addon/+package.namespace+/+package.namespace2+/+package.name+/configure.zcml.bob
bobtemplates/eea/addon/+package.namespace+/+package.namespace2+/+package.name+/interfaces.py.bob
bobtemplates/eea/addon/+package.namespace+/+package.namespace2+/+package.name+/profiles.zcml.bob
bobtemplates/eea/addon/+package.namespace+/+package.namespace2+/+package.name+/setuphandlers.py.bob
bobtemplates/eea/addon/+package.namespace+/+package.namespace2+/+package.name+/version.txt.bob
bobtemplates/eea/addon/+package.namespace+/+package.namespace2+/+package.name+/browser/__init__.py
