Metadata-Version: 2.1
Name: bobtemplates.eea
Version: 4.0.9
Summary: Templates for Plone projects.
Home-page: https://github.com/plone/bobtemplates.eea
Author: Plone Foundation
Author-email: plone-developers@lists.sourceforge.net
License: GPL version 2
Keywords: web plone zope skeleton project
Platform: UNKNOWN
Classifier: Environment :: Console
Classifier: Intended Audience :: Developers
Classifier: Natural Language :: English
Classifier: Operating System :: OS Independent
Classifier: Programming Language :: Python
Classifier: Programming Language :: Python :: 2.7
Classifier: Programming Language :: Python :: 3.7
Classifier: Programming Language :: Python :: Implementation :: CPython
Classifier: Development Status :: 5 - Production/Stable
Classifier: Topic :: Software Development :: Code Generators
Classifier: Topic :: Utilities
Classifier: License :: OSI Approved :: GNU General Public License v2 (GPLv2)
License-File: LICENSE.GPL
License-File: LICENSE.rst
